{"CPLEXSolution": {"header": {"solved_by": "cplex_local", "objectiveValue": "6", "problemName": "NASL_Scheduling"}, "variables": [{"index": "36", "name": "h_4_1", "value": "1.0"}, {"index": "37", "name": "a_4_1", "value": "1.0"}, {"index": "68", "name": "h_6_5", "value": "1.0"}, {"index": "69", "name": "a_6_5", "value": "1.0"}, {"index": "78", "name": "h_7_4", "value": "1.0"}, {"index": "79", "name": "a_7_4", "value": "1.0"}, {"index": "107", "name": "x_2_4_1", "value": "1.0"}, {"index": "112", "name": "x_3_1_1", "value": "1.0"}, {"index": "133", "name": "x_5_6_1", "value": "1.0"}, {"index": "151", "name": "x_7_8_1", "value": "1.0"}, {"index": "164", "name": "x_1_5_2", "value": "1.0"}, {"index": "182", "name": "x_3_7_2", "value": "1.0"}, {"index": "201", "name": "x_6_2_2", "value": "1.0"}, {"index": "219", "name": "x_8_4_2", "value": "1.0"}, {"index": "234", "name": "x_2_3_3", "value": "1.0"}, {"index": "248", "name": "x_4_1_3", "value": "1.0"}, {"index": "263", "name": "x_5_8_3", "value": "1.0"}, {"index": "277", "name": "x_7_6_3", "value": "1.0"}, {"index": "294", "name": "x_1_7_4", "value": "1.0"}, {"index": "308", "name": "x_3_5_4", "value": "1.0"}, {"index": "331", "name": "x_6_4_4", "value": "1.0"}, {"index": "345", "name": "x_8_2_4", "value": "1.0"}, {"index": "360", "name": "x_2_1_5", "value": "1.0"}, {"index": "378", "name": "x_4_3_5", "value": "1.0"}, {"index": "390", "name": "x_5_7_5", "value": "1.0"}, {"index": "413", "name": "x_8_6_5", "value": "1.0"}, {"index": "421", "name": "x_1_6_6", "value": "1.0"}, {"index": "439", "name": "x_3_8_6", "value": "1.0"}, {"index": "449", "name": "x_5_2_6", "value": "1.0"}, {"index": "467", "name": "x_7_4_6", "value": "1.0"}, {"index": "494", "name": "x_2_7_7", "value": "1.0"}, {"index": "508", "name": "x_4_5_7", "value": "1.0"}, {"index": "522", "name": "x_6_3_7", "value": "1.0"}, {"index": "536", "name": "x_8_1_7", "value": "1.0"}], "version": "1.0", "linearConstraints": [{"index": 0, "name": null}, {"index": 1, "name": null}, {"index": 2, "name": null}, {"index": 3, "name": null}, {"index": 4, "name": null}, {"index": 5, "name": null}, {"index": 6, "name": null}, {"index": 7, "name": null}, {"index": 8, "name": null}, {"index": 9, "name": null}, {"index": 10, "name": null}, {"index": 11, "name": null}, {"index": 12, "name": null}, {"index": 13, "name": null}, {"index": 14, "name": null}, {"index": 15, "name": null}, {"index": 16, "name": null}, {"index": 17, "name": null}, {"index": 18, "name": null}, {"index": 19, "name": null}, {"index": 20, "name": null}, {"index": 21, "name": null}, {"index": 22, "name": null}, {"index": 23, "name": null}, {"index": 24, "name": null}, {"index": 25, "name": null}, {"index": 26, "name": null}, {"index": 27, "name": null}, {"index": 28, "name": null}, {"index": 29, "name": null}, {"index": 30, "name": null}, {"index": 31, "name": null}, {"index": 32, "name": null}, {"index": 33, "name": null}, {"index": 34, "name": null}, {"index": 35, "name": null}, {"index": 36, "name": null}, {"index": 37, "name": null}, {"index": 38, "name": null}, {"index": 39, "name": null}, {"index": 40, "name": null}, {"index": 41, "name": null}, {"index": 42, "name": null}, {"index": 43, "name": null}, {"index": 44, "name": null}, {"index": 45, "name": null}, {"index": 46, "name": null}, {"index": 47, "name": null}, {"index": 48, "name": null}, {"index": 49, "name": null}, {"index": 50, "name": null}, {"index": 51, "name": null}, {"index": 52, "name": null}, {"index": 53, "name": null}, {"index": 54, "name": null}, {"index": 55, "name": null}, {"index": 56, "name": null}, {"index": 57, "name": null}, {"index": 58, "name": null}, {"index": 59, "name": null}, {"index": 60, "name": null}, {"index": 61, "name": null}, {"index": 62, "name": null}, {"index": 63, "name": null}, {"index": 64, "name": null}, {"index": 65, "name": null}, {"index": 66, "name": null}, {"index": 67, "name": null}, {"index": 68, "name": null}, {"index": 69, "name": null}, {"index": 70, "name": null}, {"index": 71, "name": null}, {"index": 72, "name": null}, {"index": 73, "name": null}, {"index": 74, "name": null}, {"index": 75, "name": null}, {"index": 76, "name": null}, {"index": 77, "name": null}, {"index": 78, "name": null}, {"index": 79, "name": null}, {"index": 80, "name": null}, {"index": 81, "name": null}, {"index": 82, "name": null}, {"index": 83, "name": null}, {"index": 84, "name": null}, {"index": 85, "name": null}, {"index": 86, "name": null}, {"index": 87, "name": null}, {"index": 88, "name": null}, {"index": 89, "name": null}, {"index": 90, "name": null}, {"index": 91, "name": null}, {"index": 92, "name": null}, {"index": 93, "name": null}, {"index": 94, "name": null}, {"index": 95, "name": null}, {"index": 96, "name": null}, {"index": 97, "name": null}, {"index": 98, "name": null}, {"index": 99, "name": null}, {"index": 100, "name": null}, {"index": 101, "name": null}, {"index": 102, "name": null}, {"index": 103, "name": null}, {"index": 104, "name": null}, {"index": 105, "name": null}, {"index": 106, "name": null}, {"index": 107, "name": null}, {"index": 108, "name": null}, {"index": 109, "name": null}, {"index": 110, "name": null}, {"index": 111, "name": null}, {"index": 112, "name": null}, {"index": 113, "name": null}, {"index": 114, "name": null}, {"index": 115, "name": null}, {"index": 116, "name": null}, {"index": 117, "name": null}, {"index": 118, "name": null}, {"index": 119, "name": null}, {"index": 120, "name": null}, {"index": 121, "name": null}, {"index": 122, "name": null}, {"index": 123, "name": null}, {"index": 124, "name": null}, {"index": 125, "name": null}, {"index": 126, "name": null}, {"index": 127, "name": null}, {"index": 128, "name": null}, {"index": 129, "name": null}, {"index": 130, "name": null}, {"index": 131, "name": null}, {"index": 132, "name": null}, {"index": 133, "name": null}, {"index": 134, "name": null}, {"index": 135, "name": null}, {"index": 136, "name": null}, {"index": 137, "name": null}, {"index": 138, "name": null}, {"index": 139, "name": null}, {"index": 140, "name": null}, {"index": 141, "name": null}, {"index": 142, "name": null}, {"index": 143, "name": null}, {"index": 144, "name": null}, {"index": 145, "name": null}, {"index": 146, "name": null}, {"index": 147, "name": null}, {"index": 148, "name": null}, {"index": 149, "name": null}, {"index": 150, "name": null}, {"index": 151, "name": null}, {"index": 152, "name": null}, {"index": 153, "name": null}, {"index": 154, "name": null}, {"index": 155, "name": null}, {"index": 156, "name": null}, {"index": 157, "name": null}, {"index": 158, "name": null}, {"index": 159, "name": null}, {"index": 160, "name": null}, {"index": 161, "name": null}, {"index": 162, "name": null}, {"index": 163, "name": null}, {"index": 164, "name": null}, {"index": 165, "name": null}, {"index": 166, "name": null}, {"index": 167, "name": null}, {"index": 168, "name": null, "slack": 1.0}, {"index": 169, "name": null}, {"index": 170, "name": null}, {"index": 171, "name": null, "slack": 1.0}, {"index": 172, "name": null}, {"index": 173, "name": null, "slack": 1.0}, {"index": 174, "name": null, "slack": 1.0}, {"index": 175, "name": null}, {"index": 176, "name": null}, {"index": 177, "name": null, "slack": -1.0}, {"index": 178, "name": null, "slack": -1.0}, {"index": 179, "name": null}, {"index": 180, "name": null, "slack": -1.0}, {"index": 181, "name": null}, {"index": 182, "name": null}, {"index": 183, "name": null, "slack": -1.0}, {"index": 184, "name": null, "slack": 1.0}, {"index": 185, "name": null, "slack": 1.0}, {"index": 186, "name": null, "slack": 1.0}, {"index": 187, "name": null}, {"index": 188, "name": null, "slack": 1.0}, {"index": 189, "name": null}, {"index": 190, "name": null}, {"index": 191, "name": null, "slack": 1.0}, {"index": 192, "name": null, "slack": 1.0}, {"index": 193, "name": null, "slack": 1.0}, {"index": 194, "name": null, "slack": 1.0}, {"index": 195, "name": null}, {"index": 196, "name": null, "slack": 1.0}, {"index": 197, "name": null}, {"index": 198, "name": null}, {"index": 199, "name": null, "slack": 1.0}, {"index": 200, "name": null}, {"index": 201, "name": null}, {"index": 202, "name": null}, {"index": 203, "name": null}, {"index": 204, "name": null}, {"index": 205, "name": null}, {"index": 206, "name": null}, {"index": 207, "name": null}, {"index": 208, "name": null}, {"index": 209, "name": null}, {"index": 210, "name": null}, {"index": 211, "name": null}, {"index": 212, "name": null, "slack": 1.0}, {"index": 213, "name": null}, {"index": 214, "name": null}, {"index": 215, "name": null}, {"index": 216, "name": null}, {"index": 217, "name": null}, {"index": 218, "name": null}, {"index": 219, "name": null}, {"index": 220, "name": null}, {"index": 221, "name": null}, {"index": 222, "name": null}, {"index": 223, "name": null}, {"index": 224, "name": null}, {"index": 225, "name": null}, {"index": 226, "name": null}, {"index": 227, "name": null}, {"index": 228, "name": null, "slack": 1.0}, {"index": 229, "name": null}, {"index": 230, "name": null}, {"index": 231, "name": null}, {"index": 232, "name": null}, {"index": 233, "name": null}, {"index": 234, "name": null}, {"index": 235, "name": null}, {"index": 236, "name": null}, {"index": 237, "name": null}, {"index": 238, "name": null}, {"index": 239, "name": null}, {"index": 240, "name": null}, {"index": 241, "name": null}, {"index": 242, "name": null}, {"index": 243, "name": null}, {"index": 244, "name": null}, {"index": 245, "name": null, "slack": 1.0}, {"index": 246, "name": null}, {"index": 247, "name": null}, {"index": 248, "name": null}, {"index": 249, "name": null}, {"index": 250, "name": null}, {"index": 251, "name": null}, {"index": 252, "name": null}, {"index": 253, "name": null}, {"index": 254, "name": null}, {"index": 255, "name": null}, {"index": 256, "name": null}, {"index": 257, "name": null}, {"index": 258, "name": null}, {"index": 259, "name": null}, {"index": 260, "name": null, "slack": 1.0}, {"index": 261, "name": null}, {"index": 262, "name": null}, {"index": 263, "name": null}, {"index": 264, "name": null}, {"index": 265, "name": null}, {"index": 266, "name": null}, {"index": 267, "name": null}, {"index": 268, "name": null}, {"index": 269, "name": null}, {"index": 270, "name": null}, {"index": 271, "name": null}, {"index": 272, "name": null}, {"index": 273, "name": null}, {"index": 274, "name": null}, {"index": 275, "name": null}, {"index": 276, "name": null, "slack": 1.0}, {"index": 277, "name": null}, {"index": 278, "name": null}, {"index": 279, "name": null}, {"index": 280, "name": null}, {"index": 281, "name": null}, {"index": 282, "name": null}, {"index": 283, "name": null}, {"index": 284, "name": null}, {"index": 285, "name": null}, {"index": 286, "name": null}, {"index": 287, "name": null}, {"index": 288, "name": null}, {"index": 289, "name": null}, {"index": 290, "name": null}, {"index": 291, "name": null}, {"index": 292, "name": null}, {"index": 293, "name": null, "slack": 1.0}, {"index": 294, "name": null}, {"index": 295, "name": null}]}}